mikado/__init__.py
mikado/core/__init__.py
mikado/core/config.py
mikado_core-0.0.3.data/scripts/releaseinator.py
mikado_core-0.0.3.data/scripts/releaseinator.py~
mikado_core-0.0.3.dist-info/DESCRIPTION.rst
mikado_core-0.0.3.dist-info/METADATA
mikado_core-0.0.3.dist-info/RECORD
mikado_core-0.0.3.dist-info/WHEEL
mikado_core-0.0.3.dist-info/metadata.json
mikado_core-0.0.3.dist-info/top_level.txt
