Metadata-Version: 2.0
Name: mikado-core
Version: 0.0.3
Summary: Core files for Mikado Software OSS projects
Home-page: UNKNOWN
Author: paul@mikadosoftware.com
Author-email: UNKNOWN
License: UNKNOWN
Platform: UNKNOWN
